ren/__init__.py
ren/__main__.py
ren/emoji.py
ren/formatter.py
ren/logging.py
ren/options.py
ren/ren.py
ren_cli-0.1.5.dist-info/METADATA
ren_cli-0.1.5.dist-info/WHEEL
ren_cli-0.1.5.dist-info/entry_points.txt
ren_cli-0.1.5.dist-info/top_level.txt
ren_cli-0.1.5.dist-info/RECORD
